.gitignore
LICENSE
README.md
setup.py
jmapd/__init__.py
jmapd/app.py
jmapd/main.py
jmapd.egg-info/PKG-INFO
jmapd.egg-info/SOURCES.txt
jmapd.egg-info/dependency_links.txt
jmapd.egg-info/entry_points.txt
jmapd.egg-info/requires.txt
jmapd.egg-info/top_level.txt
jmapd/model/__init__.py
jmapd/model/_base.py
jmapd/model/core.py
jmapd/model/log.py
jmapd/model/mail.py
jmapd/service/__init__.py
jmapd/service/core.py
jmapd/service/mail.py