Metadata-Version: 2.1
Name: jmapd
Version: 0.1.0a0
Summary: A JMAP server implementation
Home-page: https://github.com/arskom/jmapd
Author: Burak Arslan
Author-email: inbox@burakarslan.com
License: UNKNOWN
Platform: UNKNOWN
Classifier: Programming Language :: Python :: 2.7
Classifier: Programming Language :: Python :: 3
Classifier: License :: OSI Approved :: BSD License
Classifier: Operating System :: OS Independent
Requires-Python: >=2.7
